bsb_json/__init__.py
bsb_json/parser.py
bsb_json/schema/__init__.py
bsb_json/templates/__init__.py
bsb_json/templates/skeleton.json
bsb_json/templates/starting_example.json
bsb_json-7.2.1.dist-info/entry_points.txt
bsb_json-7.2.1.dist-info/licenses/LICENSE
bsb_json-7.2.1.dist-info/WHEEL
bsb_json-7.2.1.dist-info/METADATA
bsb_json-7.2.1.dist-info/RECORD
